superrezolver2208.py
superrezolver2208-0.0.1.dist-info/WHEEL
superrezolver2208-0.0.1.dist-info/METADATA
superrezolver2208-0.0.1.dist-info/RECORD
