Metadata-Version: 2.1
Name: superrezolver2208
Version: 0.0.1
Summary: BY REZOLVER
Author: Your Name
Author-email: you@example.com
Requires-Python: >=2.7,<3.0
Classifier: Programming Language :: Python :: 2
Classifier: Programming Language :: Python :: 2.7
